faust_bootstrap/__init__.py
faust_bootstrap/core/__init__.py
faust_bootstrap/core/app/__init__.py
faust_bootstrap/core/app/app_faust.py
faust_bootstrap/core/streams/__init__.py
faust_bootstrap/core/streams/agent_utils.py
faust_bootstrap/core/streams/cli.py
faust_bootstrap/core/streams/commands.py
faust_bootstrap/core/streams/exceptions.py
faust_bootstrap/core/streams/models.py
faust_bootstrap/core/streams/schemas.py
faust_bootstrap/core/streams/utils.py
faust_bootstrap-1.2.0.dist-info/LICENSE
faust_bootstrap-1.2.0.dist-info/WHEEL
faust_bootstrap-1.2.0.dist-info/METADATA
faust_bootstrap-1.2.0.dist-info/RECORD
