Metadata-Version: 2.1
Name: faust-bootstrap
Version: 1.2.0
Summary: Faust bootstrap app
Home-page: https://github.com/bakdata/faust-bootstrap
Author: bakdata
Requires-Python: >=3.6
Classifier: Programming Language :: Python :: 3
Classifier: Programming Language :: Python
Classifier: Topic :: Internet
Classifier: Topic :: Software Development :: Libraries :: Application Frameworks
Classifier: Topic :: Software Development :: Libraries :: Python Modules
Classifier: Topic :: Software Development :: Libraries
Classifier: Topic :: Software Development
Classifier: Typing :: Typed
Classifier: Intended Audience :: Developers
Classifier: License :: OSI Approved :: MIT License
Classifier: Programming Language :: Python :: 3 :: Only
Classifier: Programming Language :: Python :: 3.6
Classifier: Programming Language :: Python :: 3.7
Classifier: Programming Language :: Python :: 3.8
Requires-Dist: python-schema-registry-client==1.8.2
Requires-Dist: faust-streaming
Requires-Dist: confluent-kafka
Requires-Dist: typing-extensions==3.7.4
Requires-Dist: faust-avro-serializer==1.1.0
Requires-Dist: bump2version
Requires-Dist: pytest ; extra == "test"
Requires-Dist: pytest-cov ; extra == "test"
Requires-Dist: pytest-docker ; extra == "test"
Requires-Dist: pytest-asyncio ; extra == "test"
Provides-Extra: test
